setup.py
gaubin_probab/Binomialdistribution.py
gaubin_probab/Gaussiandistribution.py
gaubin_probab/Generaldistribution.py
gaubin_probab/__init__.py
gaubin_probab.egg-info/PKG-INFO
gaubin_probab.egg-info/SOURCES.txt
gaubin_probab.egg-info/dependency_links.txt
gaubin_probab.egg-info/not-zip-safe
gaubin_probab.egg-info/top_level.txt