Metadata-Version: 1.0
Name: gaubin-probab
Version: 0.1
Summary: Gaussian and Binomial distributions
Home-page: UNKNOWN
Author: Ashish Kumar
Author-email: luck.ashish@gmail.com
License: UNKNOWN
Platform: UNKNOWN
